{
   "Buildings": [{"address":"delhi","id":1},
    {"address":"karachi","id":2},{"address":"firozabad","id":3},{"address":"sundarnagar","id":4},{"address":"palwal","id":5},{"address":"mathura","id":6},{"address":"chennai","id":7},{"address":"varanasi","id":8},{"address":"gaya","id":9},{"address":"ballabgarh","id":10},{"address":"dwarka","id":11},{"address":"mumbai","id":12},{"address":"kedarnath","id":13},{"address":"hyderabad","id":14},{"address":"jabalpur","id":15},{"address":"banglore","id":16},{"address":"kolkata","id":17},{"address":"dheradun","id":18},{"address":"panipath","id":19},{"address":"panaji","id":20},{"address":"kochi","id":21},{"address":"assam","id":22},{"address":"gurugram","id":23},{"address":"rachi","id":24},{"address":"chandigarh","id":25},{"address":"rudrapur","id":26},{"address":"faridabad","id":27},{"address":"mohali","id":28},{"address":"bhopal","id":29},{"address":"shimla","id":30},{"address":"noida","id":31}]

}